shwirl/__init__.py
shwirl/regrid.py
shwirl/shwirl.py
shwirl/extern/__init__.py
shwirl/extern/vispy/__init__.py
shwirl/extern/vispy/app/__init__.py
shwirl/extern/vispy/app/_default_app.py
shwirl/extern/vispy/app/application.py
shwirl/extern/vispy/app/base.py
shwirl/extern/vispy/app/canvas.py
shwirl/extern/vispy/app/inputhook.py
shwirl/extern/vispy/app/qt.py
shwirl/extern/vispy/app/timer.py
shwirl/extern/vispy/app/backends/__init__.py
shwirl/extern/vispy/app/backends/_egl.py
shwirl/extern/vispy/app/backends/_glfw.py
shwirl/extern/vispy/app/backends/_ipynb_static.py
shwirl/extern/vispy/app/backends/_ipynb_util.py
shwirl/extern/vispy/app/backends/_ipynb_vnc.py
shwirl/extern/vispy/app/backends/_ipynb_webgl.py
shwirl/extern/vispy/app/backends/_osmesa.py
shwirl/extern/vispy/app/backends/_pyglet.py
shwirl/extern/vispy/app/backends/_pyqt4.py
shwirl/extern/vispy/app/backends/_pyqt5.py
shwirl/extern/vispy/app/backends/_pyside.py
shwirl/extern/vispy/app/backends/_qt.py
shwirl/extern/vispy/app/backends/_sdl2.py
shwirl/extern/vispy/app/backends/_template.py
shwirl/extern/vispy/app/backends/_test.py
shwirl/extern/vispy/app/backends/_wx.py
shwirl/extern/vispy/app/backends/ipython/__init__.py
shwirl/extern/vispy/app/backends/ipython/_widget.py
shwirl/extern/vispy/app/backends/tests/__init__.py
shwirl/extern/vispy/app/backends/tests/test_ipynb_util.py
shwirl/extern/vispy/app/tests/__init__.py
shwirl/extern/vispy/app/tests/test_app.py
shwirl/extern/vispy/app/tests/test_backends.py
shwirl/extern/vispy/app/tests/test_context.py
shwirl/extern/vispy/app/tests/test_interactive.py
shwirl/extern/vispy/app/tests/test_ipython.py
shwirl/extern/vispy/app/tests/test_qt.py
shwirl/extern/vispy/app/tests/test_simultaneous.py
shwirl/extern/vispy/color/__init__.py
shwirl/extern/vispy/color/_color_dict.py
shwirl/extern/vispy/color/color_array.py
shwirl/extern/vispy/color/color_space.py
shwirl/extern/vispy/color/colormap.py
shwirl-0.1.4.dist-info/DESCRIPTION.rst
shwirl-0.1.4.dist-info/METADATA
shwirl-0.1.4.dist-info/RECORD
shwirl-0.1.4.dist-info/WHEEL
shwirl-0.1.4.dist-info/entry_points.txt
shwirl-0.1.4.dist-info/metadata.json
shwirl-0.1.4.dist-info/top_level.txt
